LICENSE
MANIFEST.in
README.md
setup.py
deepstochlog/__init__.py
deepstochlog/context.py
deepstochlog/dataloader.py
deepstochlog/dataset.py
deepstochlog/inferences.py
deepstochlog/logic.py
deepstochlog/model.py
deepstochlog/network.py
deepstochlog/networkevaluation.py
deepstochlog/nn_models.py
deepstochlog/parser.py
deepstochlog/rule.py
deepstochlog/tabled_and_or_trees.py
deepstochlog/tabled_tree_builder.py
deepstochlog/term.py
deepstochlog/trainer.py
deepstochlog/utils.py
deepstochlog.egg-info/PKG-INFO
deepstochlog.egg-info/SOURCES.txt
deepstochlog.egg-info/dependency_links.txt
deepstochlog.egg-info/requires.txt
deepstochlog.egg-info/top_level.txt