Metadata-Version: 2.1
Name: deepstochlog
Version: 0.0.1
Summary: Neural Stochastic Logic Programming
Home-page: UNKNOWN
Author: Thomas Winters, Giuseppe Marra, Robin Manhaeve, Luc De Raedt
Author-email: firstname.lastname@kuleuven.be
License: Apache License 2.0
Platform: UNKNOWN
Requires-Python: >=3
